flask_sockets/__init__.py
flask_sockets/contrib/__init__.py
Flask_Sockets_Tornado-0.1.1.dist-info/METADATA
Flask_Sockets_Tornado-0.1.1.dist-info/top_level.txt
Flask_Sockets_Tornado-0.1.1.dist-info/DESCRIPTION.rst
Flask_Sockets_Tornado-0.1.1.dist-info/RECORD
Flask_Sockets_Tornado-0.1.1.dist-info/pbr.json
Flask_Sockets_Tornado-0.1.1.dist-info/WHEEL
Flask_Sockets_Tornado-0.1.1.dist-info/metadata.json
