Metadata-Version: 2.0
Name: Flask-Sockets-Tornado
Version: 0.1.1
Summary: Elegant WebSockets for your Flask apps.Tornado style app included
Home-page: https://github.com/winkidney/flask-sockets
Author: winkidney
Author-email: winkidney@gmail.com
License: See License
Platform: any
Classifier: Environment :: Web Environment
Classifier: Intended Audience :: Developers
Classifier: License :: OSI Approved :: BSD License
Classifier: Operating System :: OS Independent
Classifier: Programming Language :: Python
Classifier: Topic :: Internet :: WWW/HTTP :: Dynamic Content
Classifier: Topic :: Software Development :: Libraries :: Python Modules
Requires-Dist: Flask
Requires-Dist: gevent
Requires-Dist: gevent-websocket
